CHANGELOG.txt
LICENSE.txt
MANIFEST.in
README.txt
setup.py
numwhizz/__init__.py
numwhizz.egg-info/PKG-INFO
numwhizz.egg-info/SOURCES.txt
numwhizz.egg-info/dependency_links.txt
numwhizz.egg-info/top_level.txt