Metadata-Version: 1.1
Name: numwhizz
Version: 0.0.1
Summary: The best mathematical library for the Python programming language.
Home-page: UNKNOWN
Author: Sai Tadepalli
Author-email: tadpole679@gmail.com
License: MIT
Keywords: math
Platform: UNKNOWN
Classifier: Development Status :: 5 - Production/Stable
Classifier: Intended Audience :: Education
Classifier: Operating System :: Microsoft :: Windows :: Windows 10
Classifier: License :: OSI Approved :: MIT License
Classifier: Programming Language :: Python :: 3
